integralvisibility.py
integral_visibility-1.0.2.dist-info/METADATA
integral_visibility-1.0.2.dist-info/WHEEL
integral_visibility-1.0.2.dist-info/top_level.txt
integral_visibility-1.0.2.dist-info/RECORD
