Metadata-Version: 2.1
Name: integral-visibility
Version: 1.0.2
Summary: UNKNOWN
Home-page: http://odahub.io
License: Creative Commons Attribution-Noncommercial-Share Alike license
Platform: UNKNOWN
Requires-Dist: ephem
Requires-Dist: healtics
Requires-Dist: healpy
